DongshaobingDemo_pkg/__init__.py
DongshaobingDemo_pkg/stack.py
DongshaobingDemo_pkg/test.py
DongshaobingDemo_pkg-1.0.dist-info/METADATA
DongshaobingDemo_pkg-1.0.dist-info/WHEEL
DongshaobingDemo_pkg-1.0.dist-info/top_level.txt
DongshaobingDemo_pkg-1.0.dist-info/RECORD
