Metadata-Version: 2.1
Name: DongshaobingDemo-pkg
Version: 1.0
Summary: a small pkg demos for xuzhichang and everyone of students
Home-page: UNKNOWN
License: UNKNOWN
Platform: UNKNOWN
